flowtasks/__init__.py
flowtasks/__main__.py
flowtasks/utils.py
flowtasks-0.3.2.dist-info/METADATA
flowtasks-0.3.2.dist-info/WHEEL
flowtasks-0.3.2.dist-info/top_level.txt
flowtasks-0.3.2.dist-info/RECORD
