Metadata-Version: 2.1
Name: flowtasks
Version: 0.3.2
Summary: Python多进程并发调度工作流
Home-page: https://github.com/gwuhaolin/flowtasks
Author: hal
